goated/__init__.py
goated/_core.py
goated/channel.py
goated/libgoated.so
goated/result.py
goated/types.py
goated/compat/__init__.py
goated/compat/base64.py
goated/compat/hashlib.py
goated/compat/json.py
goated/compat/re.py
goated/pythonic/__init__.py
goated/pythonic/strings.py
goated/runtime/__init__.py
goated/runtime/api.py
goated/runtime/channel.py
goated/runtime/scheduler.py
goated/std/__init__.py
goated/std/base64.py
goated/std/binary.py
goated/std/bufio.py
goated/std/bytes.py
goated/std/context.py
goated/std/crypto.py
goated/std/csv.py
goated/std/errors.py
goated/std/filepath.py
goated/std/fmt.py
goated/std/goos.py
goated/std/goroutine.py
goated/std/gzip.py
goated/std/hash.py
goated/std/hex.py
goated/std/html.py
goated/std/http.py
goated/std/io.py
goated/std/json.py
goated/std/log.py
goated/std/math.py
goated/std/mime.py
goated/std/net.py
goated/std/parallel.py
goated/std/path.py
goated/std/rand.py
goated/std/regexp.py
goated/std/sort.py
goated/std/strconv.py
goated/std/strings.py
goated/std/sync.py
goated/std/template.py
goated/std/testing.py
goated/std/time.py
goated/std/unicode.py
goated/std/url.py
goated/std/utf8.py
goated/std/xml.py
goated/std/zip.py
goated_py-0.1.3.dist-info/licenses/LICENSE
goated_py-0.1.3.dist-info/METADATA
goated_py-0.1.3.dist-info/WHEEL
goated_py-0.1.3.dist-info/top_level.txt
goated_py-0.1.3.dist-info/RECORD
