Metadata-Version: 2.4
Name: goated-py
Version: 0.1.3
Summary: Go stdlib bindings for Python - Write Python, Get Go Speed
Author-email: Goated Contributors <goated@example.com>
License: MIT
Project-URL: Homepage, https://github.com/Gaurav-Gosain/goated
Project-URL: Documentation, https://github.com/Gaurav-Gosain/goated#readme
Project-URL: Repository, https://github.com/Gaurav-Gosain/goated
Project-URL: Issues, https://github.com/Gaurav-Gosain/goated/issues
Keywords: go,golang,bindings,ffi,performance,stdlib
Classifier: Development Status :: 3 - Alpha
Classifier: Intended Audience :: Developers
Classifier: License :: OSI Approved :: MIT License
Classifier: Programming Language :: Python :: 3
Classifier: Programming Language :: Python :: 3.10
Classifier: Programming Language :: Python :: 3.11
Classifier: Programming Language :: Python :: 3.12
Classifier: Programming Language :: Go
Classifier: Topic :: Software Development :: Libraries :: Python Modules
Classifier: Typing :: Typed
Requires-Python: >=3.10
License-File: LICENSE
Provides-Extra: dev
Requires-Dist: pytest>=7.0; extra == "dev"
Requires-Dist: pytest-asyncio>=0.21; extra == "dev"
Requires-Dist: pytest-benchmark>=4.0; extra == "dev"
Requires-Dist: mypy>=1.0; extra == "dev"
Requires-Dist: ruff>=0.1; extra == "dev"
Dynamic: license-file
